{"bugs":[{"severity":"S3","last_change_time":"2024-11-09T13:56:39Z","status":"NEW","summary":"tiktok.com - Live videos stop working after a few minutes, stuck loading","component":"Performance","op_sys":"Windows 10","keywords":[],"creation_time":"2024-02-14T13:36:20Z","priority":"--","id":1880287},{"op_sys":"Windows 11","keywords":[],"creation_time":"2024-07-19T09:07:38Z","priority":"P3","id":1908857,"last_change_time":"2024-09-09T14:01:12Z","severity":"--","status":"NEW","summary":"www3.nhk.or.jp - The website is loaded after 1-2 seconds of blank page","component":"Performance"},{"priority":"--","creation_time":"2024-11-21T12:52:00Z","id":1932607,"keywords":["webcompat:site-report"],"op_sys":"Windows 10","status":"NEW","summary":"nypost.com - Opening articles in multiple tabs crashes the browser (not responding)","component":"Performance","severity":"--","last_change_time":"2024-12-26T14:51:11Z"},{"last_change_time":"2025-01-06T13:36:46Z","severity":"--","component":"Performance","summary":"Deleting files from Google Drive with a huge amount of files within a folder is very slow and causes high CPU load","status":"NEW","op_sys":"Unspecified","keywords":["perf","power"],"id":1939360,"priority":"--","creation_time":"2024-12-28T21:20:57Z"},{"component":"Performance","summary":"Firefox 120.0.1 grabs 100% of cpu resources and freezes","status":"UNCONFIRMED","last_change_time":"2024-02-27T18:30:44Z","severity":"--","id":1870532,"creation_time":"2023-12-17T20:51:14Z","priority":"--","keywords":[],"op_sys":"Unspecified"},{"creation_time":"2024-02-29T23:13:16Z","priority":"--","id":1882916,"keywords":[],"op_sys":"Unspecified","summary":"Firefox consumes a lot of CPU and makes me Mac M2 hang for a good 15 seconds","status":"UNCONFIRMED","component":"Performance","severity":"--","last_change_time":"2024-05-21T13:37:47Z"},{"keywords":[],"op_sys":"Unspecified","creation_time":"2024-03-04T19:20:05Z","priority":"--","id":1883475,"severity":"--","last_change_time":"2024-10-08T17:34:50Z","summary":"huge amount of memory storage (constantly) idk why pls help/.................................................................................................................................................","status":"UNCONFIRMED","component":"Performance"},{"keywords":[],"op_sys":"Unspecified","id":1883507,"creation_time":"2024-03-04T22:03:15Z","priority":"--","last_change_time":"2024-10-08T17:35:15Z","severity":"--","component":"Performance","summary":"Memory usage is too high 23GB and up to 60% CPU usage.","status":"UNCONFIRMED"},{"last_change_time":"2024-10-08T17:34:40Z","severity":"--","component":"Performance","summary":"Memory Problem","status":"UNCONFIRMED","keywords":[],"op_sys":"Unspecified","id":1883669,"priority":"--","creation_time":"2024-03-05T15:09:26Z"},{"last_change_time":"2024-10-08T17:34:42Z","severity":"S3","component":"Performance","status":"UNCONFIRMED","summary":"Firefox is using lots of memory when only having several tabs open","keywords":["memory-footprint"],"op_sys":"Unspecified","id":1884296,"creation_time":"2024-03-08T03:56:55Z","priority":"--"},{"severity":"--","last_change_time":"2024-10-08T17:34:54Z","component":"Performance","summary":"Use to many Ram","status":"UNCONFIRMED","keywords":[],"op_sys":"Unspecified","id":1885796,"creation_time":"2024-03-17T18:24:37Z","priority":"--"},{"keywords":[],"op_sys":"Unspecified","priority":"--","creation_time":"2024-04-14T09:00:25Z","id":1891345,"last_change_time":"2024-10-08T17:35:31Z","severity":"--","status":"UNCONFIRMED","summary":"Enourmous RAM usage (60Gig)","component":"Performance"},{"severity":"--","last_change_time":"2024-11-09T15:02:19Z","component":"Performance","summary":"Extreme CPU usage spike when typing into text fields","status":"UNCONFIRMED","keywords":[],"op_sys":"Unspecified","id":1912758,"creation_time":"2024-08-12T13:10:00Z","priority":"--"},{"id":1913407,"priority":"--","creation_time":"2024-08-16T04:45:39Z","keywords":[],"op_sys":"Unspecified","component":"Performance","status":"UNCONFIRMED","summary":"the browser go crazy with cpu usage recently https://share.firefox.dev/3yIbAKI","severity":"--","last_change_time":"2024-11-09T15:22:28Z"},{"op_sys":"Unspecified","keywords":[],"creation_time":"2024-08-24T16:10:13Z","priority":"--","id":1914733,"last_change_time":"2024-09-23T21:20:52Z","severity":"--","summary":"YouTube Freezing and consuming CPU usage","status":"UNCONFIRMED","component":"Performance"},{"priority":"--","creation_time":"2024-09-11T10:37:14Z","id":1918065,"op_sys":"Unspecified","keywords":[],"summary":"High CPU/RAM utilisation using Firefox ESR without internet connectivity","status":"UNCONFIRMED","component":"Performance","last_change_time":"2024-12-02T11:07:56Z","severity":"--"},{"creation_time":"2024-10-10T18:25:27Z","priority":"--","id":1923941,"op_sys":"Windows 11","keywords":[],"summary":"Firefox stops responding, 23 seconds in gfxDWriteFontList::ReadFaceNamesForFamily","status":"UNCONFIRMED","component":"Performance","severity":"--","last_change_time":"2024-12-31T10:59:46Z"},{"status":"UNCONFIRMED","summary":"Parent process and content processes sometimes consume lots of CPU (Tons of IPCOut — PContent::Msg_ScriptError)","component":"Performance","severity":"--","last_change_time":"2024-12-26T14:10:54Z","creation_time":"2024-10-15T08:05:21Z","priority":"--","id":1924642,"keywords":[],"op_sys":"Unspecified"},{"component":"Performance","status":"UNCONFIRMED","summary":"since update 115.17.0esr (64 bits) my computer freezes and firefox takes 100% of the memory","severity":"--","last_change_time":"2024-12-26T14:21:04Z","id":1929575,"creation_time":"2024-11-06T14:38:42Z","priority":"--","keywords":["perf"],"op_sys":"Unspecified"},{"severity":"--","last_change_time":"2024-12-26T14:36:27Z","summary":"Slow poor scrolling performance when using dual monitors.","status":"UNCONFIRMED","component":"Performance","keywords":[],"op_sys":"Windows 10","creation_time":"2024-11-14T16:01:57Z","priority":"--","id":1931371},{"keywords":[],"op_sys":"Unspecified","priority":"--","creation_time":"2024-12-24T16:19:48Z","id":1939043,"last_change_time":"2025-01-06T12:55:17Z","severity":"--","status":"UNCONFIRMED","summary":"Gmail freezes on 2nd Gmail account","component":"Performance"},{"status":"UNCONFIRMED","summary":"slowness","component":"Performance","last_change_time":"2025-01-06T12:59:45Z","severity":"--","priority":"--","creation_time":"2024-12-30T13:04:04Z","id":1939474,"keywords":[],"op_sys":"Unspecified"}]}