{"bugs":[{"id":1852924,"status":"ASSIGNED","keywords":["leave-open","perf:responsiveness","reproducible","top50","webcompat:platform-bug"],"summary":"H3 upload Speed still slow. Three times slower than other browsers.","creation_time":"2023-09-13T10:36:04Z","priority":"P1","component":"Networking: HTTP","op_sys":"Unspecified","severity":"S2","last_change_time":"2025-04-08T13:48:34Z"},{"last_change_time":"2025-03-18T17:25:18Z","component":"Storage: Quota Manager","severity":"S2","op_sys":"Unspecified","priority":"P1","summary":"Frequent long janks on Android on loading certain pages","creation_time":"2024-06-19T11:50:31Z","keywords":[],"status":"ASSIGNED","id":1903530},{"last_change_time":"2024-05-16T14:42:52Z","component":"Widget: Cocoa","severity":"S2","op_sys":"Unspecified","priority":"P2","status":"NEW","id":1602842,"summary":"OSXDisplay::EnableVsync hangs in CVDisplayLinkCreateWithActiveCGDisplays","creation_time":"2019-12-10T17:22:25Z","keywords":["perf:responsiveness"]},{"op_sys":"Unspecified","severity":"--","component":"Performance: General","last_change_time":"2025-03-11T08:41:57Z","priority":"--","summary":"[Meta] investigate performance issues on Reddit.","creation_time":"2021-01-28T16:03:57Z","keywords":["meta"],"id":1689392,"status":"NEW"},{"last_change_time":"2025-03-11T12:38:29Z","op_sys":"Unspecified","component":"Web Audio","severity":"S3","priority":"P2","status":"NEW","id":1771179,"summary":"AudioContext power optimizations","creation_time":"2022-05-25T16:56:04Z","keywords":[]},{"id":1788530,"status":"NEW","keywords":["perf:resource-use","perf:responsiveness","reproducible"],"creation_time":"2022-08-31T21:19:22Z","summary":"Fenix hangs and memory usage jumps on theguardian.com when opening headlines in new tab","priority":"P2","severity":"S2","op_sys":"Unspecified","component":"Performance","last_change_time":"2025-03-10T23:42:15Z"},{"status":"NEW","id":1892234,"summary":"org.mozilla.experiments.nimbus.Nimbus$applyLocalExperiments$2$1.invoke blocks startup for 110ms while it's loading libxul","creation_time":"2024-04-18T13:42:25Z","keywords":["regression","regressionwindow-wanted"],"last_change_time":"2025-04-08T14:27:50Z","component":"Experimentation and Telemetry","severity":"S2","op_sys":"Android","priority":"P2"},{"id":1928948,"status":"NEW","creation_time":"2024-11-04T09:34:27Z","summary":"vizzy.io - The browser is slowed down and eventually stops responding","keywords":["webcompat:needs-contact","webcompat:site-report"],"op_sys":"Windows 10","severity":"S2","component":"Site Reports","last_change_time":"2025-03-20T03:11:36Z","priority":"P2"},{"op_sys":"Unspecified","severity":"S2","component":"Crash Reporting","last_change_time":"2023-10-11T11:59:19Z","priority":"--","summary":"ContentParent::KillHard janks the main thread","creation_time":"2019-05-10T14:52:25Z","keywords":["perf:responsiveness","perf:startup","reproducible"],"id":1550754,"status":"REOPENED"}]}